CHANGELOG.md
README.md
image_preview_thumbnailer.py
pelican_plugin_image_preview_thumbnailer-1.0.8.dist-info/LICENSE.txt
pelican_plugin_image_preview_thumbnailer-1.0.8.dist-info/WHEEL
pelican_plugin_image_preview_thumbnailer-1.0.8.dist-info/METADATA
pelican_plugin_image_preview_thumbnailer-1.0.8.dist-info/RECORD
