Metadata-Version: 2.1
Name: pelican-plugin-image-preview-thumbnailer
Version: 1.0.8
Summary: Pelican plugin that insert thumbnails along image links
Home-page: https://github.com/pelican-plugins/image-preview-thumbnailer
License: AGPL-3.0
Keywords: pelican,plugin,image,preview,thumbnail
Author: Lucas Cimon
Author-email: lucas.cimon@gmail.com
Requires-Python: >=3.6,<4.0
Classifier: Development Status :: 5 - Production/Stable
Classifier: Environment :: Console
Classifier: Framework :: Pelican
Classifier: Framework :: Pelican :: Plugins
Classifier: Intended Audience :: End Users/Desktop
Classifier: License :: OSI Approved :: GNU Affero General Public License v3
Classifier: Operating System :: OS Independent
Classifier: Programming Language :: Python
Classifier: Programming Language :: Python :: 3
Classifier: Programming Language :: Python :: 3.6
Classifier: Programming Language :: Python :: 3.7
Classifier: Programming Language :: Python :: 3.8
Classifier: Programming Language :: Python :: 3.9
Classifier: Topic :: Internet :: WWW/HTTP
Classifier: Topic :: Software Development :: Libraries :: Python Modules
Provides-Extra: markdown
Requires-Dist: Pillow (>=8.3.1,<9.0.0)
Requires-Dist: beautifulsoup4 (>=4.8.2,<5.0.0)
Requires-Dist: requests (>=2.22.0,<3.0.0)
Project-URL: Documentation, https://docs.getpelican.com/
Project-URL: Funding, https://donate.getpelican.com/
Project-URL: Repository, https://github.com/pelican-plugins/image-preview-thumbnailer
Project-URL: Source, https://github.com/pelican-plugins/image-preview-thumbnailer
Project-URL: Tracker, https://github.com/pelican-plugins/image-preview-thumbnailer/issues
